grapes/__init__.py
grapes/config.py
grapes/main.py
grapes/aws/__init__.py
grapes/aws/client.py
grapes/aws/fetcher.py
grapes/aws/metrics.py
grapes/models/__init__.py
grapes/models/cluster.py
grapes/models/health.py
grapes/models/service.py
grapes/models/task.py
grapes/ui/__init__.py
grapes/ui/app.py
grapes/ui/cluster_view.py
grapes/ui/console_link.py
grapes/ui/debug_console.py
grapes/ui/metrics_panel.py
grapes/ui/service_view.py
grapes/ui/styles.css
grapes/ui/task_view.py
grapes/ui/tree_view.py
grapes/utils/__init__.py
grapes/utils/ids.py
grapes_ecs-0.2.0.dist-info/METADATA
grapes_ecs-0.2.0.dist-info/WHEEL
grapes_ecs-0.2.0.dist-info/entry_points.txt
grapes_ecs-0.2.0.dist-info/licenses/LICENSE
grapes_ecs-0.2.0.dist-info/RECORD
