Metadata-Version: 2.4
Name: grapes-ecs
Version: 0.2.0
Summary: Single pane TUI for monitoring AWS ECS cluster health
Project-URL: Homepage, https://github.com/onyxfish/grapes
Project-URL: Repository, https://github.com/onyxfish/grapes
Project-URL: Issues, https://github.com/onyxfish/grapes/issues
Author: Christopher Groskopf
License-Expression: MIT
License-File: LICENSE
Keywords: aws,ecs,monitoring,terminal,textual,tui
Classifier: Development Status :: 4 - Beta
Classifier: Environment :: Console
Classifier: Intended Audience :: Developers
Classifier: Intended Audience :: System Administrators
Classifier: License :: OSI Approved :: MIT License
Classifier: Operating System :: OS Independent
Classifier: Programming Language :: Python :: 3
Classifier: Programming Language :: Python :: 3.11
Classifier: Programming Language :: Python :: 3.12
Classifier: Programming Language :: Python :: 3.13
Classifier: Topic :: System :: Monitoring
Classifier: Topic :: Utilities
Requires-Python: >=3.11
Requires-Dist: boto3>=1.34.0
Requires-Dist: pyperclip>=1.8.2
Requires-Dist: rich>=13.7.0
Requires-Dist: textual>=0.47.0
